django_sticky_uploads-1.0.0.dist-info/DESCRIPTION.rst
django_sticky_uploads-1.0.0.dist-info/METADATA
django_sticky_uploads-1.0.0.dist-info/RECORD
django_sticky_uploads-1.0.0.dist-info/WHEEL
django_sticky_uploads-1.0.0.dist-info/metadata.json
django_sticky_uploads-1.0.0.dist-info/top_level.txt
stickyuploads/__init__.py
stickyuploads/forms.py
stickyuploads/models.py
stickyuploads/storage.py
stickyuploads/urls.py
stickyuploads/utils.py
stickyuploads/views.py
stickyuploads/widgets.py
stickyuploads/static/stickyuploads/js/django-uploader.js
stickyuploads/static/stickyuploads/js/django-uploader.min.js
stickyuploads/tests/__init__.py
stickyuploads/tests/base.py
stickyuploads/tests/test_forms.py
stickyuploads/tests/test_integration.py
stickyuploads/tests/test_utils.py
stickyuploads/tests/test_views.py
stickyuploads/tests/test_widgets.py
stickyuploads/tests/urls.py
