Metadata-Version: 2.0
Name: django-sticky-uploads
Version: 1.0.0
Summary: Enhanced file input widget for Django which uploads the file in the background and retains value on form errors.
Home-page: https://github.com/caktus/django-sticky-uploads/
Author: Caktus Consulting Group
Author-email: solutions@caktusgroup.com
License: BSD
Platform: UNKNOWN
Classifier: Topic :: Internet :: WWW/HTTP :: Dynamic Content
Classifier: Intended Audience :: Developers
Classifier: License :: OSI Approved :: BSD License
Classifier: Programming Language :: Python
Classifier: Programming Language :: Python :: 2
Classifier: Programming Language :: Python :: 2.7
Classifier: Programming Language :: Python :: 3
Classifier: Programming Language :: Python :: 3.2
Classifier: Programming Language :: Python :: 3.3
Classifier: Framework :: Django
Classifier: Development Status :: 4 - Beta
Classifier: Operating System :: OS Independent
